Metadata-Version: 1.0
Name: xyz-distributions
Version: 0.1
Summary: Gaussian distributions
Home-page: UNKNOWN
Author: Codeninja
Author-email: student@udacity.com
License: UNKNOWN
Platform: UNKNOWN
